{"dir": "2", "angebote": {"0": {"sel": false, "t": "TCK#2660#2670#0#0#S2#2240#", "c": "S2", "p": "22,40", "tt": "SP", "zb": "Y", "arq": "N", "ff": "OLT-OBU", "aix": "0", "sids": ["19"], "risids": [], "pky": "72660", "angnm": "72660", "kotxt": "72660", "ueid": "4", "uepr1": "1900", "uepr2": "$2", "uepr3": "$2", "uentg": "0"}, "1": {"sel": false, "t": "TCK#2660#2668#0#0#S2#2690#", "c": "S2", "p": "26,90", "tt": "SP", "zb": "Y", "arq": "N", "ff": "OLT-OBU", "aix": "1", "sids": ["21"], "risids": [], "pky": "72660", "angnm": "72660", "kotxt": "72660", "ueid": "4", "uepr1": "1900", "uepr2": "$2", "uepr3": "$2", "uentg": "0"}, "2": {"sel": false, "t": "TCK#2660#2667#0#0#S2#2990#", "c": "S2", "p": "29,90", "tt": "SP", "zb": "Y", "arq": "N", "ff": "OLT-OBU", "aix": "2", "sids": ["0"], "risids": [], "pky": "72660", "angnm": "72660", "kotxt": "72660", "ueid": "4", "uepr1": "1900", "uepr2": "$2", "uepr3": "$2", "uentg": "0"}, "3": {"sel": false, "t": "TCK#2660#2666#0#0#S2#3590#", "c": "S2", "p": "35,90", "tt": "SP", "zb": "Y", "arq": "N", "ff": "OLT-OBU", "aix": "3", "sids": ["3"], "risids": [], "pky": "72660", "angnm": "72660", "kotxt": "72660", "ueid": "4", "uepr1": "1900", "uepr2": "$2", "uepr3": "$2", "uentg": "0"}, "4": {"sel": false, "t": "TCK#2660#2665#0#0#S2#4040#", "c": "S2", "p": "40,40", "tt": "SP", "zb": "Y", "arq": "N", "ff": "OLT-OBU", "aix": "4", "sids": ["2", "20"], "risids": [], "pky": "72660", "angnm": "72660", "kotxt": "72660", "ueid": "4", "uepr1": "1900", "uepr2": "$2", "uepr3": "$2", "uentg": "0"}, "5": {"sel": false, "t": "TCK#2660#2664#0#0#S2#4490#", "c": "S2", "p": "44,90", "tt": "SP", "zb": "Y", "arq": "N", "ff": "OLT-OBU", "aix": "5", "sids": ["1"], "risids": [], "pky": "72660", "angnm": "72660", "kotxt": "72660", "ueid": "4", "uepr1": "1900", "uepr2": "$2", "uepr3": "$2", "uentg": "0"}, "6": {"sel": false, "t": "TCK#2660#2663#0#0#S2#5240#", "c": "S2", "p": "52,40", "tt": "SP", "zb": "Y", "arq": "N", "ff": "OLT-OBU", "aix": "6", "sids": ["4", "15", "16"], "risids": [], "pky": "72660", "angnm": "72660", "kotxt": "72660", "ueid": "4", "uepr1": "1900", "uepr2": "$2", "uepr3": "$2", "uentg": "0"}, "7": {"sel": false, "t": "TCK#2660#2662#0#0#S2#5990#", "c": "S2", "p": "59,90", "tt": "SP", "zb": "Y", "arq": "N", "ff": "OLT-OBU", "aix": "7", "sids": ["5", "6", "7", "9", "10", "11", "12", "14", "17"], "risids": [], "pky": "72660", "angnm": "72660", "kotxt": "72660", "ueid": "4", "uepr1": "1900", "uepr2": "$2", "uepr3": "$2", "uentg": "0"}, "8": {"sel": false, "t": "TCK#2660#2661#0#0#S2#6740#", "c": "S2", "p": "67,40", "tt": "SP", "zb": "Y", "arq": "N", "ff": "OLT-OBU", "aix": "8", "sids": ["18"], "risids": [], "pky": "72660", "angnm": "72660", "kotxt": "72660", "ueid": "4", "uepr1": "1900", "uepr2": "$2", "uepr3": "$2", "uentg": "0"}, "9": {"sel": false, "t": "TCK#1#0#0#0#S2#7800#", "c": "S2", "p": "78,00", "tt": "NP", "zb": "N", "arq": "N", "ff": "OLT-OBU", "aix": "9", "sids": ["8", "13"], "risids": [], "pky": "7001", "angnm": "7001", "kotxt": "7001", "ueid": "4", "uepr1": "$1", "uepr2": "1900", "uepr3": "1900", "uentg": "0"}}, "verbindungen": {"11": {"sel": false, "dir": "OUTWARD", "sid": "11", "dt": "23.02.18", "dur": "3:41", "nt": "2", "NZVerb": false, "eg": "ICE", "trains": [{"tid": "11.0", "lt": "Transport", "ltShort": "T", "s": "8000284", "sn": "N\u00fcrnberg Hbf", "d": "8010101", "dn": "Erfurt Hbf", "tn": "ICE  706", "eg": "ICE", "dep": {"d": "23.02.18", "t": "14:55", "m": "1519394100000"}, "arr": {"d": "23.02.18", "t": "16:24", "m": "1519399440000"}, "pd": "7", "pa": "9", "rp": false, "re": false, "sp": false}, {"tid": "11.1", "lt": "Transport", "ltShort": "T", "s": "8010101", "sn": "Erfurt Hbf", "d": "8010205", "dn": "Leipzig Hbf", "tn": "ICE  598", "eg": "ICE", "dep": {"d": "23.02.18", "t": "16:28", "m": "1519399680000"}, "arr": {"d": "23.02.18", "t": "17:09", "m": "1519402140000"}, "pd": "10", "pa": "11", "rp": false, "re": false, "sp": false}, {"tid": "11.2", "lt": "Transport", "ltShort": "T", "s": "8010205", "sn": "Leipzig Hbf", "d": "8010085", "dn": "Dresden Hbf", "tn": "IC  2049", "eg": "IC", "dep": {"d": "23.02.18", "t": "17:31", "m": "1519403460000"}, "arr": {"d": "23.02.18", "t": "18:36", "m": "1519407360000"}, "pd": "14", "pa": "3", "rp": false, "re": false, "sp": false}]}, "12": {"sel": false, "dir": "OUTWARD", "sid": "12", "dt": "23.02.18", "dur": "4:37", "nt": "2", "NZVerb": false, "eg": "ICE", "trains": [{"tid": "12.0", "lt": "Transport", "ltShort": "T", "s": "8000284", "sn": "N\u00fcrnberg Hbf", "d": "8010159", "dn": "Halle(Saale)Hbf", "tn": "ICE  706", "eg": "ICE", "dep": {"d": "23.02.18", "t": "14:55", "m": "1519394100000"}, "arr": {"d": "23.02.18", "t": "17:04", "m": "1519401840000"}, "pd": "7", "pa": "8", "rp": false, "re": false, "sp": false}, {"tid": "12.1", "lt": "Transport", "ltShort": "T", "s": "8010159", "sn": "Halle(Saale)Hbf", "d": "8098205", "dn": "Leipzig Hbf (tief)", "tn": "S     5X", "eg": "S", "dep": {"d": "23.02.18", "t": "17:15", "m": "1519402500000"}, "arr": {"d": "23.02.18", "t": "17:38", "m": "1519403880000"}, "pd": "13", "pa": "1", "rp": false, "re": false, "sp": false}, {"tid": "12.2", "lt": "Transport", "ltShort": "T", "s": "8010205", "sn": "Leipzig Hbf", "d": "8010085", "dn": "Dresden Hbf", "tn": "RE 16529", "eg": "RE", "dep": {"d": "23.02.18", "t": "18:00", "m": "1519405200000"}, "arr": {"d": "23.02.18", "t": "19:32", "m": "1519410720000"}, "pd": "21", "pa": "10", "rp": false, "re": false, "sp": false}]}, "13": {"sel": false, "dir": "OUTWARD", "sid": "13", "dt": "23.02.18", "dur": "3:31", "nt": "1", "NZVerb": false, "eg": "ICE", "trains": [{"tid": "13.0", "lt": "Transport", "ltShort": "T", "s": "8000284", "sn": "N\u00fcrnberg Hbf", "d": "8010205", "dn": "Leipzig Hbf", "tn": "ICE 1506", "eg": "ICE", "dep": {"d": "23.02.18", "t": "16:05", "m": "1519398300000"}, "arr": {"d": "23.02.18", "t": "18:10", "m": "1519405800000"}, "pd": "7", "pa": "11", "rp": false, "re": false, "sp": false}, {"tid": "13.1", "lt": "Transport", "ltShort": "T", "s": "8010205", "sn": "Leipzig Hbf", "d": "8010085", "dn": "Dresden Hbf", "tn": "ICE 1653", "eg": "ICE", "dep": {"d": "23.02.18", "t": "18:31", "m": "1519407060000"}, "arr": {"d": "23.02.18", "t": "19:36", "m": "1519410960000"}, "pd": "12", "pa": "3", "rp": false, "re": false, "sp": false}]}, "14": {"sel": false, "dir": "OUTWARD", "sid": "14", "dt": "23.02.18", "dur": "4:07", "nt": "1", "NZVerb": false, "eg": "ICE", "trains": [{"tid": "14.0", "lt": "Transport", "ltShort": "T", "s": "8000284", "sn": "N\u00fcrnberg Hbf", "d": "8010159", "dn": "Halle(Saale)Hbf", "tn": "ICE 1726", "eg": "ICE", "dep": {"d": "23.02.18", "t": "16:29", "m": "1519399740000"}, "arr": {"d": "23.02.18", "t": "18:37", "m": "1519407420000"}, "pd": "7", "pa": "12", "rp": false, "re": false, "sp": false}, {"tid": "14.1", "lt": "Transport", "ltShort": "T", "s": "8010159", "sn": "Halle(Saale)Hbf", "d": "8010085", "dn": "Dresden Hbf", "tn": "IC  2047", "eg": "IC", "dep": {"d": "23.02.18", "t": "18:54", "m": "1519408440000"}, "arr": {"d": "23.02.18", "t": "20:36", "m": "1519414560000"}, "pd": "9", "pa": "3", "rp": false, "re": false, "sp": false}]}, "15": {"sel": false, "dir": "OUTWARD", "sid": "15", "dt": "23.02.18", "dur": "3:31", "nt": "2", "NZVerb": false, "eg": "ICE", "trains": [{"tid": "15.0", "lt": "Transport", "ltShort": "T", "s": "8000284", "sn": "N\u00fcrnberg Hbf", "d": "8010101", "dn": "Erfurt Hbf", "tn": "ICE  704", "eg": "ICE", "dep": {"d": "23.02.18", "t": "17:05", "m": "1519401900000"}, "arr": {"d": "23.02.18", "t": "18:24", "m": "1519406640000"}, "pd": "7", "pa": "9", "rp": false, "re": false, "sp": false}, {"tid": "15.1", "lt": "Transport", "ltShort": "T", "s": "8010101", "sn": "Erfurt Hbf", "d": "8010205", "dn": "Leipzig Hbf", "tn": "ICE  596", "eg": "ICE", "dep": {"d": "23.02.18", "t": "18:28", "m": "1519406880000"}, "arr": {"d": "23.02.18", "t": "19:09", "m": "1519409340000"}, "pd": "10", "pa": "11", "rp": false, "re": false, "sp": false}, {"tid": "15.2", "lt": "Transport", "ltShort": "T", "s": "8010205", "sn": "Leipzig Hbf", "d": "8010085", "dn": "Dresden Hbf", "tn": "IC  2047", "eg": "IC", "dep": {"d": "23.02.18", "t": "19:31", "m": "1519410660000"}, "arr": {"d": "23.02.18", "t": "20:36", "m": "1519414560000"}, "pd": "14", "pa": "3", "rp": false, "re": false, "sp": false}]}, "16": {"sel": false, "dir": "OUTWARD", "sid": "16", "dt": "23.02.18", "dur": "4:27", "nt": "2", "NZVerb": false, "eg": "ICE", "trains": [{"tid": "16.0", "lt": "Transport", "ltShort": "T", "s": "8000284", "sn": "N\u00fcrnberg Hbf", "d": "8010159", "dn": "Halle(Saale)Hbf", "tn": "ICE  704", "eg": "ICE", "dep": {"d": "23.02.18", "t": "17:05", "m": "1519401900000"}, "arr": {"d": "23.02.18", "t": "19:04", "m": "1519409040000"}, "pd": "7", "pa": "8", "rp": false, "re": false, "sp": false}, {"tid": "16.1", "lt": "Transport", "ltShort": "T", "s": "8010159", "sn": "Halle(Saale)Hbf", "d": "8098205", "dn": "Leipzig Hbf (tief)", "tn": "S     5X", "eg": "S", "dep": {"d": "23.02.18", "t": "19:15", "m": "1519409700000"}, "arr": {"d": "23.02.18", "t": "19:38", "m": "1519411080000"}, "pd": "13", "pa": "1", "rp": false, "re": false, "sp": false}, {"tid": "16.2", "lt": "Transport", "ltShort": "T", "s": "8010205", "sn": "Leipzig Hbf", "d": "8010085", "dn": "Dresden Hbf", "tn": "RE 16533", "eg": "RE", "dep": {"d": "23.02.18", "t": "20:00", "m": "1519412400000"}, "arr": {"d": "23.02.18", "t": "21:32", "m": "1519417920000"}, "pd": "21", "pa": "10", "rp": false, "re": false, "sp": false}]}, "17": {"sel": false, "dir": "OUTWARD", "sid": "17", "dt": "23.02.18", "dur": "3:31", "nt": "1", "NZVerb": false, "eg": "ICE", "trains": [{"tid": "17.0", "lt": "Transport", "ltShort": "T", "s": "8000284", "sn": "N\u00fcrnberg Hbf", "d": "8010205", "dn": "Leipzig Hbf", "tn": "ICE 1504", "eg": "ICE", "dep": {"d": "23.02.18", "t": "18:05", "m": "1519405500000"}, "arr": {"d": "23.02.18", "t": "20:10", "m": "1519413000000"}, "pd": "7", "pa": "11", "rp": false, "re": false, "sp": false}, {"tid": "17.1", "lt": "Transport", "ltShort": "T", "s": "8010205", "sn": "Leipzig Hbf", "d": "8010085", "dn": "Dresden Hbf", "tn": "ICE 1655", "eg": "ICE", "dep": {"d": "23.02.18", "t": "20:31", "m": "1519414260000"}, "arr": {"d": "23.02.18", "t": "21:36", "m": "1519418160000"}, "pd": "12", "pa": "3", "rp": false, "re": false, "sp": false}]}, "18": {"sel": false, "dir": "OUTWARD", "sid": "18", "dt": "23.02.18", "dur": "3:36", "nt": "1", "NZVerb": false, "eg": "ICE", "trains": [{"tid": "18.0", "lt": "Transport", "ltShort": "T", "s": "8000284", "sn": "N\u00fcrnberg Hbf", "d": "8010159", "dn": "Halle(Saale)Hbf", "tn": "ICE 1000", "eg": "ICE", "dep": {"d": "23.02.18", "t": "19:00", "m": "1519408800000"}, "arr": {"d": "23.02.18", "t": "20:38", "m": "1519414680000"}, "pd": "7", "pa": "8", "rp": false, "re": false, "sp": false}, {"tid": "18.1", "lt": "Transport", "ltShort": "T", "s": "8010159", "sn": "Halle(Saale)Hbf", "d": "8010085", "dn": "Dresden Hbf", "tn": "IC  2045", "eg": "IC", "dep": {"d": "23.02.18", "t": "20:54", "m": "1519415640000"}, "arr": {"d": "23.02.18", "t": "22:36", "m": "1519421760000"}, "pd": "9", "pa": "3", "rp": false, "re": false, "sp": false}]}, "19": {"sel": false, "dir": "OUTWARD", "sid": "19", "dt": "23.02.18", "dur": "3:31", "nt": "2", "NZVerb": false, "eg": "ICE", "trains": [{"tid": "19.0", "lt": "Transport", "ltShort": "T", "s": "8000284", "sn": "N\u00fcrnberg Hbf", "d": "8010101", "dn": "Erfurt Hbf", "tn": "ICE  702", "eg": "ICE", "dep": {"d": "23.02.18", "t": "19:05", "m": "1519409100000"}, "arr": {"d": "23.02.18", "t": "20:24", "m": "1519413840000"}, "pd": "8", "pa": "9", "rp": false, "re": false, "sp": false}, {"tid": "19.1", "lt": "Transport", "ltShort": "T", "s": "8010101", "sn": "Erfurt Hbf", "d": "8010205", "dn": "Leipzig Hbf", "tn": "ICE  594", "eg": "ICE", "dep": {"d": "23.02.18", "t": "20:28", "m": "1519414080000"}, "arr": {"d": "23.02.18", "t": "21:09", "m": "1519416540000"}, "pd": "10", "pa": "11", "rp": false, "re": false, "sp": false}, {"tid": "19.2", "lt": "Transport", "ltShort": "T", "s": "8010205", "sn": "Leipzig Hbf", "d": "8010085", "dn": "Dresden Hbf", "tn": "IC  2045", "eg": "IC", "dep": {"d": "23.02.18", "t": "21:31", "m": "1519417860000"}, "arr": {"d": "23.02.18", "t": "22:36", "m": "1519421760000"}, "pd": "14", "pa": "3", "rp": false, "re": false, "sp": false}]}, "0": {"sel": false, "dir": "OUTWARD", "sid": "0", "dt": "23.02.18", "dur": "3:51", "nt": "1", "NZVerb": false, "eg": "ICE", "trains": [{"tid": "0.0", "lt": "Transport", "ltShort": "T", "s": "8000284", "sn": "N\u00fcrnberg Hbf", "d": "8010205", "dn": "Leipzig Hbf", "tn": "ICE 1516", "eg": "ICE", "dep": {"d": "23.02.18", "t": "05:45", "m": "1519361100000"}, "arr": {"d": "23.02.18", "t": "08:08", "m": "1519369680000"}, "pd": "4", "pa": "11", "rp": false, "re": false, "sp": false}, {"tid": "0.1", "lt": "Transport", "ltShort": "T", "s": "8010205", "sn": "Leipzig Hbf", "d": "8010085", "dn": "Dresden Hbf", "tn": "ICE 1553", "eg": "ICE", "dep": {"d": "23.02.18", "t": "08:31", "m": "1519371060000"}, "arr": {"d": "23.02.18", "t": "09:36", "m": "1519374960000"}, "pd": "12", "pa": "17", "rp": false, "re": false, "sp": false}]}, "1": {"sel": false, "dir": "OUTWARD", "sid": "1", "dt": "23.02.18", "dur": "3:36", "nt": "1", "NZVerb": false, "eg": "ICE", "trains": [{"tid": "1.0", "lt": "Transport", "ltShort": "T", "s": "8000284", "sn": "N\u00fcrnberg Hbf", "d": "8010159", "dn": "Halle(Saale)Hbf", "tn": "ICE 1008", "eg": "ICE", "dep": {"d": "23.02.18", "t": "07:00", "m": "1519365600000"}, "arr": {"d": "23.02.18", "t": "08:38", "m": "1519371480000"}, "pd": "7", "pa": "9", "rp": false, "re": false, "sp": false}, {"tid": "1.1", "lt": "Transport", "ltShort": "T", "s": "8010159", "sn": "Halle(Saale)Hbf", "d": "8010085", "dn": "Dresden Hbf", "tn": "IC  2447", "eg": "IC", "dep": {"d": "23.02.18", "t": "08:54", "m": "1519372440000"}, "arr": {"d": "23.02.18", "t": "10:36", "m": "1519378560000"}, "pd": "9", "pa": "3", "rp": false, "re": false, "sp": false}]}, "2": {"sel": false, "dir": "OUTWARD", "sid": "2", "dt": "23.02.18", "dur": "3:31", "nt": "1", "NZVerb": false, "eg": "ICE", "trains": [{"tid": "2.0", "lt": "Transport", "ltShort": "T", "s": "8000284", "sn": "N\u00fcrnberg Hbf", "d": "8010205", "dn": "Leipzig Hbf", "tn": "ICE 1514", "eg": "ICE", "dep": {"d": "23.02.18", "t": "08:05", "m": "1519369500000"}, "arr": {"d": "23.02.18", "t": "10:10", "m": "1519377000000"}, "pd": "6", "pa": "11", "rp": false, "re": false, "sp": false}, {"tid": "2.1", "lt": "Transport", "ltShort": "T", "s": "8010205", "sn": "Leipzig Hbf", "d": "8010085", "dn": "Dresden Hbf", "tn": "ICE 1555", "eg": "ICE", "dep": {"d": "23.02.18", "t": "10:31", "m": "1519378260000"}, "arr": {"d": "23.02.18", "t": "11:36", "m": "1519382160000"}, "pd": "12", "pa": "3", "rp": false, "re": false, "sp": false}]}, "3": {"sel": false, "dir": "OUTWARD", "sid": "3", "dt": "23.02.18", "dur": "3:31", "nt": "2", "NZVerb": false, "eg": "ICE", "trains": [{"tid": "3.0", "lt": "Transport", "ltShort": "T", "s": "8000284", "sn": "N\u00fcrnberg Hbf", "d": "8010101", "dn": "Erfurt Hbf", "tn": "ICE  802", "eg": "ICE", "dep": {"d": "23.02.18", "t": "09:05", "m": "1519373100000"}, "arr": {"d": "23.02.18", "t": "10:24", "m": "1519377840000"}, "pd": "7", "pa": "9", "rp": false, "re": false, "sp": false}, {"tid": "3.1", "lt": "Transport", "ltShort": "T", "s": "8010101", "sn": "Erfurt Hbf", "d": "8010205", "dn": "Leipzig Hbf", "tn": "ICE  694", "eg": "ICE", "dep": {"d": "23.02.18", "t": "10:28", "m": "1519378080000"}, "arr": {"d": "23.02.18", "t": "11:09", "m": "1519380540000"}, "pd": "10", "pa": "11", "rp": false, "re": false, "sp": false}, {"tid": "3.2", "lt": "Transport", "ltShort": "T", "s": "8010205", "sn": "Leipzig Hbf", "d": "8010085", "dn": "Dresden Hbf", "tn": "IC  2445", "eg": "IC", "dep": {"d": "23.02.18", "t": "11:31", "m": "1519381860000"}, "arr": {"d": "23.02.18", "t": "12:36", "m": "1519385760000"}, "pd": "14", "pa": "3", "rp": false, "re": false, "sp": false}]}, "4": {"sel": false, "dir": "OUTWARD", "sid": "4", "dt": "23.02.18", "dur": "3:31", "nt": "1", "NZVerb": false, "eg": "ICE", "trains": [{"tid": "4.0", "lt": "Transport", "ltShort": "T", "s": "8000284", "sn": "N\u00fcrnberg Hbf", "d": "8010205", "dn": "Leipzig Hbf", "tn": "ICE 1512", "eg": "ICE", "dep": {"d": "23.02.18", "t": "10:05", "m": "1519376700000"}, "arr": {"d": "23.02.18", "t": "12:10", "m": "1519384200000"}, "pd": "6", "pa": "11", "rp": false, "re": false, "sp": false}, {"tid": "4.1", "lt": "Transport", "ltShort": "T", "s": "8010205", "sn": "Leipzig Hbf", "d": "8010085", "dn": "Dresden Hbf", "tn": "ICE 1557", "eg": "ICE", "dep": {"d": "23.02.18", "t": "12:31", "m": "1519385460000"}, "arr": {"d": "23.02.18", "t": "13:36", "m": "1519389360000"}, "pd": "12", "pa": "3", "rp": false, "re": false, "sp": false}]}, "5": {"sel": false, "dir": "OUTWARD", "sid": "5", "dt": "23.02.18", "dur": "3:58", "nt": "3", "NZVerb": false, "eg": "ICE", "trains": [{"tid": "5.0", "lt": "Transport", "ltShort": "T", "s": "8000284", "sn": "N\u00fcrnberg Hbf", "d": "8000025", "dn": "Bamberg", "tn": "RE  4986", "eg": "RE", "dep": {"d": "23.02.18", "t": "10:38", "m": "1519378680000"}, "arr": {"d": "23.02.18", "t": "11:20", "m": "1519381200000"}, "pd": "4", "pa": "6", "rp": false, "re": false, "sp": false}, {"tid": "5.1", "lt": "Transport", "ltShort": "T", "s": "8000025", "sn": "Bamberg", "d": "8010101", "dn": "Erfurt Hbf", "tn": "ICE  800", "eg": "ICE", "dep": {"d": "23.02.18", "t": "11:40", "m": "1519382400000"}, "arr": {"d": "23.02.18", "t": "12:24", "m": "1519385040000"}, "pd": "6", "pa": "9", "rp": false, "re": false, "sp": false}, {"tid": "5.2", "lt": "Transport", "ltShort": "T", "s": "8010101", "sn": "Erfurt Hbf", "d": "8010205", "dn": "Leipzig Hbf", "tn": "ICE  692", "eg": "ICE", "dep": {"d": "23.02.18", "t": "12:28", "m": "1519385280000"}, "arr": {"d": "23.02.18", "t": "13:09", "m": "1519387740000"}, "pd": "10", "pa": "11", "rp": false, "re": false, "sp": false}, {"tid": "5.3", "lt": "Transport", "ltShort": "T", "s": "8010205", "sn": "Leipzig Hbf", "d": "8010085", "dn": "Dresden Hbf", "tn": "IC  2443", "eg": "IC", "dep": {"d": "23.02.18", "t": "13:31", "m": "1519389060000"}, "arr": {"d": "23.02.18", "t": "14:36", "m": "1519392960000"}, "pd": "14", "pa": "3", "rp": false, "re": false, "sp": false}]}, "6": {"sel": false, "dir": "OUTWARD", "sid": "6", "dt": "23.02.18", "dur": "3:33", "nt": "2", "NZVerb": false, "eg": "ICE", "trains": [{"tid": "6.0", "lt": "Transport", "ltShort": "T", "s": "8000284", "sn": "N\u00fcrnberg Hbf", "d": "8010101", "dn": "Erfurt Hbf", "tn": "ICE  800", "eg": "ICE", "dep": {"d": "23.02.18", "t": "11:03", "m": "1519380180000"}, "arr": {"d": "23.02.18", "t": "12:24", "m": "1519385040000"}, "pd": "7", "pa": "9", "rp": false, "re": false, "sp": false}, {"tid": "6.1", "lt": "Transport", "ltShort": "T", "s": "8010101", "sn": "Erfurt Hbf", "d": "8010205", "dn": "Leipzig Hbf", "tn": "ICE  692", "eg": "ICE", "dep": {"d": "23.02.18", "t": "12:28", "m": "1519385280000"}, "arr": {"d": "23.02.18", "t": "13:09", "m": "1519387740000"}, "pd": "10", "pa": "11", "rp": false, "re": false, "sp": false}, {"tid": "6.2", "lt": "Transport", "ltShort": "T", "s": "8010205", "sn": "Leipzig Hbf", "d": "8010085", "dn": "Dresden Hbf", "tn": "IC  2443", "eg": "IC", "dep": {"d": "23.02.18", "t": "13:31", "m": "1519389060000"}, "arr": {"d": "23.02.18", "t": "14:36", "m": "1519392960000"}, "pd": "14", "pa": "3", "rp": false, "re": false, "sp": false}]}, "7": {"sel": false, "dir": "OUTWARD", "sid": "7", "dt": "23.02.18", "dur": "3:31", "nt": "1", "NZVerb": false, "eg": "ICE", "trains": [{"tid": "7.0", "lt": "Transport", "ltShort": "T", "s": "8000284", "sn": "N\u00fcrnberg Hbf", "d": "8010205", "dn": "Leipzig Hbf", "tn": "ICE 1510", "eg": "ICE", "dep": {"d": "23.02.18", "t": "12:05", "m": "1519383900000"}, "arr": {"d": "23.02.18", "t": "14:10", "m": "1519391400000"}, "pd": "7", "pa": "11", "rp": false, "re": false, "sp": false}, {"tid": "7.1", "lt": "Transport", "ltShort": "T", "s": "8010205", "sn": "Leipzig Hbf", "d": "8010085", "dn": "Dresden Hbf", "tn": "ICE 1559", "eg": "ICE", "dep": {"d": "23.02.18", "t": "14:31", "m": "1519392660000"}, "arr": {"d": "23.02.18", "t": "15:36", "m": "1519396560000"}, "pd": "12", "pa": "3", "rp": false, "re": false, "sp": false}]}, "8": {"sel": false, "dir": "OUTWARD", "sid": "8", "dt": "23.02.18", "dur": "3:36", "nt": "1", "NZVerb": false, "eg": "ICE", "trains": [{"tid": "8.0", "lt": "Transport", "ltShort": "T", "s": "8000284", "sn": "N\u00fcrnberg Hbf", "d": "8010159", "dn": "Halle(Saale)Hbf", "tn": "ICE 1004", "eg": "ICE", "dep": {"d": "23.02.18", "t": "13:00", "m": "1519387200000"}, "arr": {"d": "23.02.18", "t": "14:38", "m": "1519393080000"}, "pd": "7", "pa": "8", "rp": false, "re": false, "sp": false}, {"tid": "8.1", "lt": "Transport", "ltShort": "T", "s": "8010159", "sn": "Halle(Saale)Hbf", "d": "8010085", "dn": "Dresden Hbf", "tn": "IC  2441", "eg": "IC", "dep": {"d": "23.02.18", "t": "14:54", "m": "1519394040000"}, "arr": {"d": "23.02.18", "t": "16:36", "m": "1519400160000"}, "pd": "9", "pa": "3", "rp": false, "re": false, "sp": false}]}, "9": {"sel": false, "dir": "OUTWARD", "sid": "9", "dt": "23.02.18", "dur": "3:31", "nt": "1", "NZVerb": false, "eg": "ICE", "trains": [{"tid": "9.0", "lt": "Transport", "ltShort": "T", "s": "8000284", "sn": "N\u00fcrnberg Hbf", "d": "8010205", "dn": "Leipzig Hbf", "tn": "ICE 1508", "eg": "ICE", "dep": {"d": "23.02.18", "t": "14:05", "m": "1519391100000"}, "arr": {"d": "23.02.18", "t": "16:10", "m": "1519398600000"}, "pd": "7", "pa": "11", "rp": false, "re": false, "sp": false}, {"tid": "9.1", "lt": "Transport", "ltShort": "T", "s": "8010205", "sn": "Leipzig Hbf", "d": "8010085", "dn": "Dresden Hbf", "tn": "ICE 1651", "eg": "ICE", "dep": {"d": "23.02.18", "t": "16:31", "m": "1519399860000"}, "arr": {"d": "23.02.18", "t": "17:36", "m": "1519403760000"}, "pd": "13", "pa": "3", "rp": false, "re": false, "sp": false}]}, "20": {"sel": false, "dir": "OUTWARD", "sid": "20", "dt": "23.02.18", "dur": "3:31", "nt": "1", "NZVerb": false, "eg": "ICE", "trains": [{"tid": "20.0", "lt": "Transport", "ltShort": "T", "s": "8000284", "sn": "N\u00fcrnberg Hbf", "d": "8010205", "dn": "Leipzig Hbf", "tn": "ICE 1502", "eg": "ICE", "dep": {"d": "23.02.18", "t": "20:05", "m": "1519412700000"}, "arr": {"d": "23.02.18", "t": "22:10", "m": "1519420200000"}, "pd": "7", "pa": "11", "rp": false, "re": false, "sp": false}, {"tid": "20.1", "lt": "Transport", "ltShort": "T", "s": "8010205", "sn": "Leipzig Hbf", "d": "8010085", "dn": "Dresden Hbf", "tn": "ICE 1657", "eg": "ICE", "dep": {"d": "23.02.18", "t": "22:31", "m": "1519421460000"}, "arr": {"d": "23.02.18", "t": "23:36", "m": "1519425360000"}, "pd": "13", "pa": "3", "rp": false, "re": false, "sp": false}]}, "10": {"sel": false, "dir": "OUTWARD", "sid": "10", "dt": "23.02.18", "dur": "4:15", "nt": "1", "NZVerb": false, "eg": "ICE", "trains": [{"tid": "10.0", "lt": "Transport", "ltShort": "T", "s": "8000284", "sn": "N\u00fcrnberg Hbf", "d": "8010159", "dn": "Halle(Saale)Hbf", "tn": "ICE 1728", "eg": "ICE", "dep": {"d": "23.02.18", "t": "14:21", "m": "1519392060000"}, "arr": {"d": "23.02.18", "t": "16:28", "m": "1519399680000"}, "pd": "7", "pa": "12", "rp": false, "re": false, "sp": false}, {"tid": "10.1", "lt": "Transport", "ltShort": "T", "s": "8010159", "sn": "Halle(Saale)Hbf", "d": "8010085", "dn": "Dresden Hbf", "tn": "IC  2049", "eg": "IC", "dep": {"d": "23.02.18", "t": "16:54", "m": "1519401240000"}, "arr": {"d": "23.02.18", "t": "18:36", "m": "1519407360000"}, "pd": "9", "pa": "3", "rp": false, "re": false, "sp": false}]}, "21": {"sel": false, "dir": "OUTWARD", "sid": "21", "dt": "23.02.18", "dur": "8:27", "nt": "2", "NZVerb": false, "eg": "ICE", "trains": [{"tid": "21.0", "lt": "Transport", "ltShort": "T", "s": "8000284", "sn": "N\u00fcrnberg Hbf", "d": "8010101", "dn": "Erfurt Hbf", "tn": "ICE  700", "eg": "ICE", "dep": {"d": "23.02.18", "t": "21:05", "m": "1519416300000"}, "arr": {"d": "23.02.18", "t": "22:37", "m": "1519421820000"}, "pd": "6", "pa": "1", "rp": false, "re": false, "sp": false}, {"tid": "21.1", "lt": "Transport", "ltShort": "T", "s": "8010101", "sn": "Erfurt Hbf", "d": "8010205", "dn": "Leipzig Hbf", "tn": "ICE  592", "eg": "ICE", "dep": {"d": "23.02.18", "t": "22:44", "m": "1519422240000"}, "arr": {"d": "23.02.18", "t": "23:23", "m": "1519424580000"}, "pd": "2", "pa": "13", "rp": false, "re": false, "sp": false}, {"tid": "21.2", "lt": "Transport", "ltShort": "T", "s": "8010205", "sn": "Leipzig Hbf", "d": "8010085", "dn": "Dresden Hbf", "tn": "RE 16501", "eg": "RE", "dep": {"d": "24.02.18", "t": "04:00", "m": "1519441200000"}, "arr": {"d": "24.02.18", "t": "05:32", "m": "1519446720000"}, "pd": "21", "pa": "10", "rp": false, "re": false, "sp": false}]}}, "peTexte": {"7001": {"name": "Flexpreis", "hinweis": "Sie k\u00f6nnen jeden Zug nutzen. Kombination mit BahnCard 25/50 und einem Rabatt von 25% bzw. 50% auf dem DB-Streckenteil m\u00f6glich.<br/>Umtausch / Erstattung vor dem 1. Geltungstag kostenlos, danach 19,00 EUR."}, "72660": {"name": "Sparpreis", "hinweis": "G\u00fcnstiger Preis, solange der Vorrat reicht. Sie k\u00f6nnen nur die Z\u00fcge nutzen, die auf Ihrer Fahrkarte angegeben sind. F\u00fcr Z\u00fcge des Nahverkehrs (z.B. RE, RB, S) besteht jedoch keine Zugbindung. Kombination mit BahnCard 25/50 und einem Rabatt von 25% m\u00f6glich.<br/>Umtausch / Erstattung vor dem 1. Geltungstag 19,00 EUR, danach ausgeschlossen."}}, "sbf": [{"nummer": "8000284", "name": "N\u00fcrnberg Hbf"}], "dbf": [{"nummer": "8010085", "name": "Dresden Hbf"}], "durs": {"min": "3:31", "max": "8:27"}, "prices": {"min": "2240", "max": "7800"}, "sp": true}